navhip/__init__.py
navhip/bitcoinTransaction.py
navhip/bitcoinVarint.py
navhip/ledgerWrapper.py
navhip/msqr.py
navhip/navhip.py
navhip/navhipComm.py
navhip/navhipException.py
navhip/navhipFirmwareWizard.py
navhip/navhipHelpers.py
navhip/navhipKeyRecovery.py
navhip/navhipPersoWizard.py
navhip/navhipUtils.py
navhip/ui/__init__.py
navhip/ui/personalization00start.py
navhip/ui/personalization01seed.py
navhip/ui/personalization02security.py
navhip/ui/personalization03config.py
navhip/ui/personalization04finalize.py
navhip/ui/personalizationseedbackup01.py
navhip/ui/personalizationseedbackup02.py
navhip/ui/personalizationseedbackup03.py
navhip/ui/personalizationseedbackup04.py
navhip_python-0.1.32.dist-info/LICENSE
navhip_python-0.1.32.dist-info/METADATA
navhip_python-0.1.32.dist-info/WHEEL
navhip_python-0.1.32.dist-info/top_level.txt
navhip_python-0.1.32.dist-info/RECORD
