Metadata-Version: 2.1
Name: navhip-python
Version: 0.1.32
Summary: Python library to communicate with Ledger Nano dongle
Home-page: https://github.com/aguycalled/navhip-python
Author: NAVhip
Author-email: alex@nav.community
Classifier: License :: OSI Approved :: Apache Software License
Classifier: Operating System :: POSIX :: Linux
Classifier: Operating System :: Microsoft :: Windows
Classifier: Operating System :: MacOS :: MacOS X
License-File: LICENSE
Requires-Dist: hidapi (>=0.7.99)
Requires-Dist: ecdsa (>=0.9)
Provides-Extra: smartcard
Requires-Dist: python-pyscard (>=1.6.12-4build1) ; extra == 'smartcard'
